LICENSE
slitherway/__init__.py
slitherway/commands.py
slitherway/models.py
slitherway-0.1.3.dist-info/LICENSE
slitherway-0.1.3.dist-info/WHEEL
slitherway-0.1.3.dist-info/METADATA
slitherway-0.1.3.dist-info/RECORD
