Metadata-Version: 2.1
Name: slitherway
Version: 0.1.3
Summary: Python wrapper for the Flyway CLI
Home-page: https://github.com/unredundant/slitherway
License: MIT
Keywords: migrations,flyway
Author: Ryan Brink
Author-email: rbweb@pm.me
Requires-Python: >=3.7,<4
Classifier: License :: OSI Approved :: MIT License
Classifier: Programming Language :: Python :: 3
Classifier: Programming Language :: Python :: 3.10
Classifier: Programming Language :: Python :: 3.7
Classifier: Programming Language :: Python :: 3.8
Classifier: Programming Language :: Python :: 3.9
Requires-Dist: pydantic (>=1.9.0,<2.0.0)
Project-URL: Repository, https://github.com/unredundant/slitherway
